pubg/__init__.py
pubg/client.py
pubg/exceptions.py
pubg/match.py
pubg/player.py
pubg/settings.py
pubg_api-0.0.2.dist-info/METADATA
pubg_api-0.0.2.dist-info/RECORD
pubg_api-0.0.2.dist-info/WHEEL
pubg_api-0.0.2.dist-info/top_level.txt
