Metadata-Version: 2.1
Name: pubg-api
Version: 0.0.2
Summary: PUBG API client
Home-page: https://github.com/imakecodes/pubg
Author: Michel Wilhelm
Author-email: michelwilhelm@gmail.com
License: UNKNOWN
Platform: UNKNOWN
Classifier: Programming Language :: Python :: 3
Classifier: License :: OSI Approved :: MIT License
Classifier: Operating System :: OS Independent
Requires-Dist: requests (>=2.19.1)
